LICENSE
MANIFEST.in
README.rst
setup.py
prox/__init__.py
prox/cmdprox.py
prox/prox
prox/pyproxmox.py
proxmox_tools.egg-info/PKG-INFO
proxmox_tools.egg-info/SOURCES.txt
proxmox_tools.egg-info/dependency_links.txt
proxmox_tools.egg-info/entry_points.txt
proxmox_tools.egg-info/requires.txt
proxmox_tools.egg-info/top_level.txt